.gitignore
HISTORY.rst
LICENSE
MANIFEST.in
README.rst
TODO
setup.py
test_narwhal.py
narwhal/__init__.py
narwhal/calc-ip.sh
narwhal/conf.py
narwhal/configure_repose.py
narwhal/download_repose.py
narwhal/maven.py
narwhal/pathutil.py
narwhal/run_repose.py
narwhal/valve.py
narwhal.egg-info/PKG-INFO
narwhal.egg-info/SOURCES.txt
narwhal.egg-info/dependency_links.txt
narwhal.egg-info/entry_points.txt
narwhal.egg-info/requires.txt
narwhal.egg-info/top_level.txt
narwhal/configs/multimatch-sspnn/.config-set.xml
narwhal/configs/multimatch-sspnn/container.cfg.xml
narwhal/configs/multimatch-sspnn/log4j.properties
narwhal/configs/multimatch-sspnn/response-messaging.cfg.xml
narwhal/configs/multimatch-sspnn/sspnn-fail.wadl
narwhal/configs/multimatch-sspnn/sspnn-nc.wadl
narwhal/configs/multimatch-sspnn/sspnn-pass.wadl
narwhal/configs/multimatch-sspnn/system-model.cfg.xml
narwhal/configs/multimatch-sspnn/validator.cfg.xml
narwhal/configs/simple-node/.config-set.xml
narwhal/configs/simple-node/container.cfg.xml
narwhal/configs/simple-node/log4j.properties
narwhal/configs/simple-node/system-model.cfg.xml
test-configs/container.cfg.xml
test-configs/log4j.properties
test-configs/response-messaging.cfg.xml
test-configs/system-model.cfg.xml