Metadata-Version: 1.1
Name: narwhal
Version: 0.7
Summary: Setup scripts for repose
Home-page: https://github.com/richard-sartor/narwhal
Author: Richard Sartor
Author-email: richard.sartor@rackspace.com
License: narwhal - Python scripts for programmatically installign and running Repose.
